autoexec/__init__.py
autoexec/autoexec.py
autoexec-0.1.1.dist-info/DESCRIPTION.rst
autoexec-0.1.1.dist-info/METADATA
autoexec-0.1.1.dist-info/RECORD
autoexec-0.1.1.dist-info/WHEEL
autoexec-0.1.1.dist-info/metadata.json
autoexec-0.1.1.dist-info/top_level.txt
