Metadata-Version: 2.0
Name: autoexec
Version: 0.1.1
Summary: Automatically turn functions into executables.
Home-page: https://github.com/befelix/autoexec
Author: Felix Berkenkamp
Author-email: fberkenkamp@gmail.com
License: MIT
Platform: UNKNOWN
Classifier: Development Status :: 3 - Alpha
Classifier: Intended Audience :: Developers
Classifier: Topic :: Software Development :: Build Tools
Classifier: License :: OSI Approved :: MIT License
Classifier: Programming Language :: Python :: 3.5
Classifier: Programming Language :: Python :: 3.6
Requires-Dist: numpydoc
